loopmon/__init__.py
loopmon/monitor.py
loopmon/py.typed
loopmon-1.0.1.dist-info/LICENSE.txt
loopmon-1.0.1.dist-info/METADATA
loopmon-1.0.1.dist-info/WHEEL
loopmon-1.0.1.dist-info/RECORD
