Metadata-Version: 2.1
Name: loopmon
Version: 1.0.1
Summary: Lightewight monitor library for asyncio.EventLoop
Home-page: https://github.com/isac322/loopmon
License: MIT
Keywords: asyncio,monitoring,eventloop,lag,delay
Author: Byeonghoon Yoo
Author-email: bh322yoo@gmail.com
Requires-Python: >=3.7,<4.0
Classifier: Development Status :: 4 - Beta
Classifier: Environment :: No Input/Output (Daemon)
Classifier: Framework :: AsyncIO
Classifier: Intended Audience :: Developers
Classifier: License :: OSI Approved :: MIT License
Classifier: Natural Language :: English
Classifier: Operating System :: OS Independent
Classifier: Programming Language :: Python
Classifier: Programming Language :: Python :: 3
Classifier: Programming Language :: Python :: 3.7
Classifier: Programming Language :: Python :: 3.8
Classifier: Programming Language :: Python :: 3.9
Classifier: Programming Language :: Python :: 3.10
Classifier: Programming Language :: Python :: 3.11
Classifier: Programming Language :: Python :: 3 :: Only
Classifier: Topic :: Scientific/Engineering
Classifier: Topic :: Scientific/Engineering :: Information Analysis
Classifier: Topic :: Software Development
Classifier: Topic :: Software Development :: Libraries
Classifier: Topic :: Software Development :: Libraries :: Python Modules
Classifier: Topic :: Software Development :: Quality Assurance
Classifier: Topic :: System
Classifier: Topic :: System :: Monitoring
Classifier: Typing :: Typed
Requires-Dist: typing-extensions (>=3.8)
Project-URL: Repository, https://github.com/isac322/loopmon
